shpg/__init__.py
shpg/_version.py
shpg/html.py
shpg/page.py
shpg/simple.py
shpg/style/default.css
shpg-0.0.2.dist-info/licenses/LICENCE
shpg-0.0.2.dist-info/METADATA
shpg-0.0.2.dist-info/WHEEL
shpg-0.0.2.dist-info/top_level.txt
shpg-0.0.2.dist-info/RECORD
