Metadata-Version: 2.4
Name: shpg
Version: 0.0.2
Summary: Create static HTML pages.
Author: Bastien Cagna
License: BSD 3
License-File: LICENCE
Provides-Extra: doc
Requires-Dist: sphinx>=1.0; extra == "doc"
Requires-Dist: furo; extra == "doc"
Requires-Dist: sphinx_design; extra == "doc"
Provides-Extra: dev
Requires-Dist: pytest; extra == "dev"
Requires-Dist: build; extra == "dev"
Requires-Dist: twine; extra == "dev"
Dynamic: author
Dynamic: description
Dynamic: description-content-type
Dynamic: license
Dynamic: license-file
Dynamic: provides-extra
Dynamic: summary
